lsi/62100186_kadai1.v
module alu_4bit (
    input [3:0] a,
    input [3:0] b,
    input [2:0] s,
    output reg [3:0] y
);

always @(*) begin
    case (s)
        3'b000: y = b;
        3'b001: y = a << 1;
        3'b010: y = a | b;
        3'b011: y = a - b;
        3'b100: y = a ^ b;
        3'b101: y = a > b;
        3'b110: y = a & b;
        3'b111: y = a + b;
        default: y = 4'd0;
    endcase
end

endmodule

lsi/tb1.v
`timescale 1ns / 1ps

module alu_4bit_tb;

  reg[3:0] a;
  reg[3:0] b;
  reg[2:0] s;
  wire [3:0] y;

  alu_4bit uut (
    .a(a),
    .b(b),
    .s(s),
    .y(y)
  );

  initial begin
    $dumpfile("62100186_kadai1.vcd");
    $dumpvars(0, alu_4bit_tb);

    s = 3'b000; a = 4'b0000; b = 4'b0000;

    s = 3'b000; a = 4'b1000; b = 4'b0110; #10;
    s = 3'b001; a = 4'b0110; b = 4'b1010; #10;
    s = 3'b010; a = 4'b1001; b = 4'b0011; #10;
    s = 3'b011; a = 4'b1100; b = 4'b0111; #10;
    s = 3'b100; a = 4'b0011; b = 4'b0000; #10;
    s = 3'b101; a = 4'b1010; b = 4'b1111; #10;
    s = 3'b110; a = 4'b1100; b = 4'b0110; #10;
    s = 3'b111; a = 4'b0111; b = 4'b0010; #10;

    $finish;
  end

endmodule

lsi/62100186_kadai1.vcd
$date
	Fri Jul 11 16:57:37 2025
$end
$version
	Icarus Verilog
$end
$timescale
	1ps
$end
$scope module alu_4bit_tb $end
$var wire 4 ! y [3:0] $end
$var reg 4 " a [3:0] $end
$var reg 4 # b [3:0] $end
$var reg 3 $ s [2:0] $end
$scope module uut $end
$var wire 4 % a [3:0] $end
$var wire 4 & b [3:0] $end
$var wire 3 ' s [2:0] $end
$var reg 4 ( y [3:0] $end
$upscope $end
$upscope $end
$enddefinitions $end
$comment Show the parameter values. $end
$dumpall
$end
#0
$dumpvars
b110 (
b0 '
b110 &
b1000 %
b0 $
b110 #
b1000 "
b110 !
$end
#10000
b1100 !
b1100 (
b1010 #
b1010 &
b110 "
b110 %
b1 $
b1 '
#20000
b1011 !
b1011 (
b11 #
b11 &
b1001 "
b1001 %
b10 $
b10 '
#30000
b101 !
b101 (
b111 #
b111 &
b1100 "
b1100 %
b11 $
b11 '
#40000
b11 !
b11 (
b0 #
b0 &
b11 "
b11 %
b100 $
b100 '
#50000
b0 !
b0 (
b1111 #
b1111 &
b1010 "
b1010 %
b101 $
b101 '
#60000
b100 !
b100 (
b110 #
b110 &
b1100 "
b1100 %
b110 $
b110 '
#70000
b1001 !
b1001 (
b10 #
b10 &
b111 "
b111 %
b111 $
b111 '
