lsi/62100186_kadai2.v
module alu_5bit (
    input [4:0] a,
    input [4:0] b,
    input [3:0] s,
    output reg [4:0] y
);

always @(*) begin
    case (s)
        4'h0:  y = a + b;
        4'h1:  y = (b >> 1) + a;
        4'h2:  y = a & b;
        4'h3:  y = ~b;
        4'h4:  y = a ^ b;
        4'h5:  y = a == b;
        4'h6:  y = a ~^ b;
        4'h7:  y = b << 1;
        4'h8:  y = a ^ b;
        4'h9:  y = b - a;
        4'hA:  y = ~a;
        4'hB:  y = a | b;
        4'hC:  y = a < b;
        4'hD:  y = b;
        4'hE:  y = a >> 1;
        4'hF:  y = a > b;
        default: y = 5'd0;
    endcase
end

endmodule

lsi/62100186_kadai2_tb.v
`timescale 1ns/1ps

module alu_5bit_tb;

  reg [4:0] a, b;
  reg [3:0] s;
  wire [4:0] y;

  alu_5bit uut (
    .a(a),
    .b(b),
    .s(s),
    .y(y)
  );

  initial begin
    $dumpfile("62100186_kadai2.vcd");
    $dumpvars(0, alu_5bit_tb);

    a = 5'h07; b = 5'h03; s = 4'h0; #10;
    a = 5'h03; b = 5'h08; s = 4'h1; #10;
    a = 5'h15; b = 5'h13; s = 4'h2; #10;
    a = 5'h01; b = 5'h0C; s = 4'h3; #10;
    a = 5'h12; b = 5'h05; s = 4'h4; #10;
    a = 5'h0A; b = 5'h0A; s = 4'h5; #10;
    a = 5'h0F; b = 5'h00; s = 4'h6; #10;
    a = 5'h00; b = 5'h04; s = 4'h7; #10;
    a = 5'h19; b = 5'h15; s = 4'h8; #10;
    a = 5'h05; b = 5'h0C; s = 4'h9; #10;
    a = 5'h06; b = 5'h00; s = 4'hA; #10;
    a = 5'h09; b = 5'h00; s = 4'hB; #10;
    a = 5'h19; b = 5'h0A; s = 4'hC; #10;
    a = 5'h00; b = 5'h15; s = 4'hD; #10;
    a = 5'h16; b = 5'h00; s = 4'hE; #10;
    a = 5'h12; b = 5'h0D; s = 4'hF; #10;

    $finish;
  end

endmodule

lsi/62100186_kadai2.vcd
$date
	Fri Jul 11 17:39:02 2025
$end
$version
	Icarus Verilog
$end
$timescale
	1ps
$end
$scope module alu_5bit_tb $end
$var wire 5 ! y [4:0] $end
$var reg 5 " a [4:0] $end
$var reg 5 # b [4:0] $end
$var reg 4 $ s [3:0] $end
$scope module uut $end
$var wire 5 % a [4:0] $end
$var wire 5 & b [4:0] $end
$var wire 4 ' s [3:0] $end
$var reg 5 ( y [4:0] $end
$upscope $end
$upscope $end
$enddefinitions $end
$comment Show the parameter values. $end
$dumpall
$end
#0
$dumpvars
b1010 (
b0 '
b11 &
b111 %
b0 $
b11 #
b111 "
b1010 !
$end
#10000
b111 !
b111 (
b1 $
b1 '
b1000 #
b1000 &
b11 "
b11 %
#20000
b10001 !
b10001 (
b10 $
b10 '
b10011 #
b10011 &
b10101 "
b10101 %
#30000
b10011 !
b10011 (
b11 $
b11 '
b1100 #
b1100 &
b1 "
b1 %
#40000
b10111 !
b10111 (
b100 $
b100 '
b101 #
b101 &
b10010 "
b10010 %
#50000
b1 !
b1 (
b101 $
b101 '
b1010 #
b1010 &
b1010 "
b1010 %
#60000
b10000 !
b10000 (
b110 $
b110 '
b0 #
b0 &
b1111 "
b1111 %
#70000
b1000 !
b1000 (
b111 $
b111 '
b100 #
b100 &
b0 "
b0 %
#80000
b1100 !
b1100 (
b1000 $
b1000 '
b10101 #
b10101 &
b11001 "
b11001 %
#90000
b111 !
b111 (
b1001 $
b1001 '
b1100 #
b1100 &
b101 "
b101 %
#100000
b11001 !
b11001 (
b1010 $
b1010 '
b0 #
b0 &
b110 "
b110 %
#110000
b1001 !
b1001 (
b1011 $
b1011 '
b1001 "
b1001 %
#120000
b0 !
b0 (
b1100 $
b1100 '
b1010 #
b1010 &
b11001 "
b11001 %
#130000
b10101 !
b10101 (
b1101 $
b1101 '
b10101 #
b10101 &
b0 "
b0 %
#140000
b1011 !
b1011 (
b1110 $
b1110 '
b0 #
b0 &
b10110 "
b10110 %
#150000
b1 !
b1 (
b1111 $
b1111 '
b1101 #
b1101 &
b10010 "
b10010 %
